{
    "d-aki.mid": {
        "note_counts": {
            "0": 90,
            "4": 68,
            "7": 90,
            "11": 20,
            "2": 39,
            "5": 35,
            "9": 40,
            "6": 8,
            "3": 2
        }
    },
    "d-aogeba.mid": {
        "note_counts": {
            "4": 31,
            "5": 24,
            "7": 32,
            "9": 33,
            "2": 18,
            "11": 20,
            "0": 40,
            "6": 1
        }
    },
    "d-aogeba_transposed+2.mid": {
        "note_counts": {
            "6": 31,
            "7": 24,
            "9": 32,
            "11": 33,
            "4": 18,
            "1": 20,
            "2": 40,
            "8": 1
        }
    },
    "d-aogeba_transposed+4.mid": {
        "note_counts": {
            "8": 31,
            "9": 24,
            "11": 32,
            "1": 33,
            "6": 18,
            "3": 20,
            "4": 40,
            "10": 1
        }
    },
    "d-aogeba_transposed-3.mid": {
        "note_counts": {
            "1": 31,
            "2": 24,
            "4": 32,
            "6": 33,
            "11": 18,
            "8": 20,
            "9": 40,
            "3": 1
        }
    },
    "d-chatu.mid": {
        "note_counts": {
            "2": 26,
            "7": 16,
            "9": 22,
            "11": 38,
            "4": 6
        }
    },
    "d-choucho.mid": {
        "note_counts": {
            "7": 11,
            "4": 23,
            "5": 6,
            "2": 13,
            "0": 3
        }
    },
    "d-haruga.mid": {
        "note_counts": {
            "6": 4,
            "7": 38,
            "9": 14,
            "10": 2,
            "11": 2,
            "4": 15,
            "5": 6,
            "0": 18,
            "2": 9
        }
    },
    "d-haruyo.mid": {
        "note_counts": {
            "1": 14,
            "11": 16,
            "9": 22,
            "6": 22,
            "4": 18
        }
    },
    "d-hiraita.mid": {
        "note_counts": {
            "9": 36,
            "7": 22,
            "4": 6,
            "11": 10,
            "2": 2
        }
    },
    "d-katatum.mid": {
        "note_counts": {
            "9": 22,
            "6": 20,
            "2": 18,
            "4": 14,
            "7": 2,
            "11": 2
        }
    },
    "d-kirakira.mid": {
        "note_counts": {
            "6": 64,
            "9": 105,
            "1": 29,
            "2": 76,
            "4": 47,
            "7": 41,
            "11": 20,
            "3": 2,
            "0": 2,
            "10": 2
        }
    },
    "d-sakura.mid": {
        "note_counts": {
            "9": 30,
            "4": 30,
            "11": 23,
            "0": 14,
            "5": 10,
            "2": 3
        }
    },
    "d-shabon.mid": {
        "note_counts": {
            "2": 24,
            "4": 10,
            "6": 10,
            "9": 16,
            "11": 11,
            "7": 2
        }
    },
    "d-tooryan.mid": {
        "note_counts": {
            "9": 66,
            "7": 24,
            "4": 26,
            "10": 40,
            "2": 30,
            "5": 36
        }
    },
    "d-uresiihina.mid": {
        "note_counts": {
            "2": 28,
            "0": 32,
            "7": 48,
            "3": 41,
            "8": 19,
            "5": 3
        }
    },
    "d-usagitokame.mid": {
        "note_counts": {
            "0": 10,
            "4": 5,
            "7": 5
        }
    },
    "d-zuizui.mid": {
        "note_counts": {
            "9": 45,
            "11": 31,
            "0": 10,
            "5": 1,
            "4": 2,
            "6": 3,
            "1": 2
        }
    }
}